src/__init__.py
src/main.py
code_updater-0.1.0.dist-info/LICENSE
code_updater-0.1.0.dist-info/METADATA
code_updater-0.1.0.dist-info/WHEEL
code_updater-0.1.0.dist-info/entry_points.txt
code_updater-0.1.0.dist-info/top_level.txt
code_updater-0.1.0.dist-info/RECORD
