Metadata-Version: 2.1
Name: code-updater
Version: 0.1.0
Summary: A Python-based tool for updating, inserting, or deleting lines in project files.
Home-page: https://github.com/joonheeu/code-updater
Author: Daniel
Author-email: daniel@udit.one
Classifier: Programming Language :: Python :: 3
Classifier: License :: OSI Approved :: MIT License
Classifier: Operating System :: OS Independent
Requires-Python: >=3.6
License-File: LICENSE
